fetchy_cli/__init__.py
fetchy_cli/__main__.py
fetchy_cli/fetchy.py
fetchy_cli-1.4.dist-info/METADATA
fetchy_cli-1.4.dist-info/WHEEL
fetchy_cli-1.4.dist-info/entry_points.txt
fetchy_cli-1.4.dist-info/top_level.txt
fetchy_cli-1.4.dist-info/RECORD
