Metadata-Version: 2.4
Name: fetchy-cli
Version: 1.4
Summary: Fetch strings from your system rather than your own memory!
Author-email: espehon <espehon@gmail.com>
License-Expression: GPL-3.0-or-later
Project-URL: Homepage, https://github.com/espehon/fetchy-cli
Project-URL: Bug Tracker, https://github.com/espehon/fetchy-cli/issues
Classifier: Programming Language :: Python :: 3
Classifier: Development Status :: 5 - Production/Stable
Classifier: Environment :: Console
Classifier: Operating System :: OS Independent
Classifier: Topic :: Utilities
Requires-Python: >=3.8
Requires-Dist: copykitten>=1.2.0
